<?xml version="1.0" encoding="utf-8"?>
<user xmlns="http://www.hymnal.net/user" version="2.0">
  <roles>USER</roles>
  <firstname>Nidia</firstname>
  <lastname/>
  <email>nidiab_delgado@yahoo.com</email>
  <password>$2y$10$IRAjaYF0L.Y7vIm/XVZJZuZI/2ERJ0u7bA6BsvzdefJcrgWWy1SBq</password>
  <gender/>
  <country>us</country>
  <ipaddress>172.56.41.243</ipaddress>
  <createdate>2014-08-08 22:00:23</createdate>
  <lastupdateddate>2014-08-08 22:27:04</lastupdateddate>
  <lastlogindate>2014-08-08 22:27:04</lastlogindate>
  <failedlogincount>0</failedlogincount>
  <favourites>
  </favourites>
</user>
