<?xml version="1.0" encoding="utf-8"?>
<user xmlns="http://www.hymnal.net/user" version="2.0">
  <roles>USER</roles>
  <firstname>Maria Jonesa</firstname>
  <lastname>Olo</lastname>
  <email>olomariajonesa@gmail.com</email>
  <password>$2y$10$5ZGnSTAubtf/IEZBD52QMuyN9og4x0YmBA3fF5cXzJTKo1Wx8LvUq</password>
  <gender/>
  <country>ph</country>
  <ipaddress>49.148.169.235</ipaddress>
  <createdate>2014-09-29 10:39:40</createdate>
  <lastupdateddate>2014-09-29 10:45:36</lastupdateddate>
  <lastlogindate>2014-09-29 10:45:36</lastlogindate>
  <failedlogincount>0</failedlogincount>
  <favourites>
  </favourites>
</user>
