<?xml version="1.0" encoding="utf-8"?>
<user xmlns="http://www.hymnal.net/user" version="1.0">
    <firstname>Christina</firstname>
    <lastname>Sakai</lastname>
    <email>christina.sakai@gmail.com</email>
    <password>QY0c2UikNRYAwSES4O3qeA%3D%3D</password>
    <gender></gender>
    <country>United States</country>
    <ipaddress>66.87.125.8</ipaddress>
    <createdate>2012-11-28 18:44:55</createdate>
    <lastupdateddate>2013-01-21 08:15:49</lastupdateddate>
    <lastlogindate>2013-01-21 08:15:49</lastlogindate>
    <failedlogincount>0</failedlogincount>
    <favourites>
    </favourites>
</user>
