<?xml version="1.0" encoding="utf-8"?>
<user xmlns="http://www.hymnal.net/user" version="1.0">
    <firstname>Beth</firstname>
    <lastname>McCance</lastname>
    <email>bmccance54@gmail.com</email>
    <password>idLT6MaZTkOlfqq%2F4qH%2FdQ%3D%3D</password>
    <gender></gender>
    <country>United States</country>
    <ipaddress>64.17.73.232</ipaddress>
    <createdate>2013-08-11 14:45:29</createdate>
    <lastupdateddate>2013-08-11 14:45:30</lastupdateddate>
    <lastlogindate>2013-08-11 14:45:30</lastlogindate>
    <failedlogincount>0</failedlogincount>
    <favourites>
    </favourites>
</user>
