<?xml version="1.0" encoding="utf-8"?>
<hymn xmlns="http://www.hymnal.net/hymn">
  <title>Oublions tout, à Christ attachons-nous</title>
  <index>true</index>
  <category>Les réunions&amp;mdash;Christ comme le centre</category>
  <numbers><cebuano num="863"/><chinese num="627"/><english num="863"/><french num="163"/><korean num="627"/><portuguese num="403"/><russian num="142"/><spanish num="390"/><tagalog num="863"/></numbers>
  <creators>
    <author biodate="1905-1997" biolink="www.witnesslee.org">Translated from Witness Lee</author>
  </creators>
  <music>
    <midiref type="h" num="556"/>
  </music>
  <lyrics>
    <stanza type="verse" number="1">Christ est le centre, Christ est tout pour nous
Dans notre vie et dans nos réunions.
Et par-delà les vérités reçues,
C'est pour Lui seul que nous nous rassemblons.</stanza>
    <stanza type="verse" number="2">Lui, le chemin, lumière de la vie,
Il nous conduit quand nous marchons en Lui.
Christ est l'eau vive, Christ est notre pain,
C'est Lui qui désaltère et rassasie.</stanza>
    <stanza type="verse" number="3">Christ est la vie, et nous Le dispensons,
La vérité, de Lui nous témoignons.
Christ est Seigneur et nous Le magnifions,
Il est la Tête que nous exaltons.</stanza>
    <stanza type="verse" number="4">Pour Dieu et l'homme, Christ est tout en tous,
Avec Lui, l'homme et Dieu sont satisfaits.
Réalité au sein de Son église,
Il se propage et Sa vie se transmet.</stanza>
    <stanza type="verse" number="5">Chantons, prions, pour exprimer ce Christ,
Qui est le centre de nos réunions.
Par Sa puissance, nous pouvons servir,
En demeurant sans cesse en communion.</stanza>
    <stanza type="verse" number="6">C'est dans Son nom que nous nous rassemblons,
Dans Son Esprit, non dans nos opinions.
Par Sa puissance, nous voulons prier,
En esprit, Le louer, bénir son nom.</stanza>
    <stanza type="verse" number="7">Oublions tout, à Christ attachons-nous,
Poursuivons-Le, cherchons-Le tous les jours.
Considérons tout comme de la boue,
Pour Le connaître, Le gagner toujours.</stanza>
  </lyrics>
</hymn>
