<?xml version="1.0" encoding="utf-8"?>
<user xmlns="http://www.hymnal.net/user" version="1.0">
    <firstname>temilade</firstname>
    <lastname></lastname>
    <email>temiladeok@yahoo.com</email>
    <password>L%2FlP2Uia5ZCc7wrGfQJBog%3D%3D</password>
    <gender></gender>
    <country>United Kingdom</country>
    <ipaddress>93.186.31.85</ipaddress>
    <createdate>2013-10-11 11:18:16</createdate>
    <lastupdateddate>2013-10-11 11:18:16</lastupdateddate>
    <lastlogindate>2013-10-11 11:18:16</lastlogindate>
    <failedlogincount>0</failedlogincount>
    <favourites>
    </favourites>
</user>
