<?xml version="1.0" encoding="utf-8"?>
<user xmlns="http://www.hymnal.net/user" version="1.0">
    <firstname>Sandy</firstname>
    <lastname>Ringel</lastname>
    <email>sandyringel@gmail.com</email>
    <password>r0oZp3ooYNxj9pEwsrYrLA%3D%3D</password>
    <gender></gender>
    <country>United States</country>
    <ipaddress>172.0.163.38</ipaddress>
    <createdate>2013-11-05 12:16:42</createdate>
    <lastupdateddate>2013-11-05 12:16:42</lastupdateddate>
    <lastlogindate>2013-11-05 12:16:42</lastlogindate>
    <failedlogincount>0</failedlogincount>
    <favourites>
    </favourites>
</user>
