<?xml version="1.0" encoding="utf-8"?>
<user xmlns="http://www.hymnal.net/user" version="1.0">
    <firstname>Spoon</firstname>
    <lastname>Anchor</lastname>
    <email>spoon9211@gmail.com</email>
    <password>VzvDCWmcJIP%2BHAD4%2B0p5Sg%3D%3D</password>
    <gender></gender>
    <country>Philippines</country>
    <ipaddress>112.198.82.11</ipaddress>
    <createdate>2014-03-30 13:24:37</createdate>
    <lastupdateddate>2014-03-30 13:24:37</lastupdateddate>
    <lastlogindate>2014-03-30 12:34:40</lastlogindate>
    <failedlogincount>0</failedlogincount>
    <favourites>
        <fav category="default" type="c" num="68">By listening I can obey</fav>
    </favourites>
</user>
