<?xml version="1.0" encoding="utf-8"?>
<user xmlns="http://www.hymnal.net/user" version="1.0">
<firstname>Janet</firstname>
<lastname>Burton</lastname>
<email>burton1941@sbcglobal.net</email>
<password>$1$SVn9Z5bU$nZEa2GMDsy7nh6JED2AIs.</password>
<gender>F</gender>
<country>United States</country>
<ipaddress>75.19.180.117</ipaddress>
<createdate>2008-07-28 14:16:42</createdate>
<lastupdateddate>2009-09-15 18:25:30</lastupdateddate>
<lastlogindate></lastlogindate>
<failedlogincount></failedlogincount>
<favourites>
    </favourites>
</user>
