<?xml version="1.0" encoding="utf-8"?>
<user xmlns="http://www.hymnal.net/user" version="1.0">
<firstname>Mark</firstname>
<lastname>Ramey</lastname>
<email>markramey1@comcast.net</email>
<password>$1$TOyzkQv7$5Z5yb3H82IvcTvhS5Xi.W0</password>
<gender>M</gender>
<country>United States</country>
<ipaddress>98.223.8.164</ipaddress>
<createdate>2008-09-01 19:28:06</createdate>
<lastupdateddate>2009-09-15 18:25:47</lastupdateddate>
<lastlogindate></lastlogindate>
<failedlogincount></failedlogincount>
<favourites>
    </favourites>
</user>
