<?xml version="1.0" encoding="utf-8"?>
<user xmlns="http://www.hymnal.net/user" version="2.0">
  <roles>USER</roles>
  <firstname>Jessie</firstname>
  <lastname>Lin</lastname>
  <email>jessielan66@gmail.com</email>
  <password>$2y$10$yR08oZNhoaBlR9D5CiVXcun05OPALAv6ISwZWI9./TD/9Ibrsv/xO</password>
  <gender/>
  <country>ca</country>
  <ipaddress>172.218.147.103</ipaddress>
  <createdate>2016-07-09 17:30:46</createdate>
  <lastupdateddate>2016-08-09 14:50:26</lastupdateddate>
  <lastlogindate>2016-08-09 14:50:26</lastlogindate>
  <failedlogincount>0</failedlogincount>
  <favourites>
  </favourites>
</user>
