<?xml version="1.0" encoding="utf-8"?>
<user xmlns="http://www.hymnal.net/user" version="2.0">
  <roles>USER</roles>
  <firstname>Semi</firstname>
  <lastname>Meo</lastname>
  <email>semi_meo@yahoo.com.au</email>
  <password>$2y$10$JJLaYdwDPeEvoqQq6QlmGexQYjvG1BzackJXQvBLBXnsZOBwOd166</password>
  <gender/>
  <country>au</country>
  <ipaddress>58.179.95.8</ipaddress>
  <createdate>2014-09-19 13:39:49</createdate>
  <lastupdateddate>2014-09-19 13:42:28</lastupdateddate>
  <lastlogindate>2014-09-19 13:42:28</lastlogindate>
  <failedlogincount>0</failedlogincount>
  <favourites>
  </favourites>
</user>
