<?xml version="1.0" encoding="utf-8"?>
<!DOCTYPE html PUBLIC "-//W3C//DTD XHTML 1.0 Transitional//EN" "http://www.w3.org/TR/xhtml1/DTD/xhtml1-transitional.dtd">
<user>    <firstname>Lewis</firstname>
    <lastname>Uriri</lastname>
    <email>lewis.uriri@lewisuriri.co.zw</email>
    <password>dutH%2Fb2PnyJAx%2BdpE9aeLw%3D%3D</password>
    <gender>M</gender>
    <country>zw</country>
    <ipaddress>197.221.240.93</ipaddress>
    <createdate>2012-10-29 14:57:03</createdate>
    <lastupdateddate>2012-10-31 03:32:00</lastupdateddate>
    <lastlogindate>2012-10-31 03:32:00</lastlogindate>
    <failedlogincount>0</failedlogincount>
    <favourites>
        <fav category="default" type="h" num="139">All hail the pow'r of Jesus' name (Medium)</fav>
        <fav category="default" type="h" num="139">All hail the pow'r of Jesus' name (Medium)</fav>
        <fav category="default" type="h" num="139">All hail the pow'r of Jesus' name (Medium)</fav>
        <fav category="default" type="h" num="296">And can it be that I should gain</fav>
        <fav category="default" type="h" num="296">And can it be that I should gain</fav>
        <fav category="default" type="h" num="296">And can it be that I should gain</fav>
        <fav category="default" type="h" num="296">And can it be that I should gain</fav>
        <fav category="default" type="h" num="296">And can it be that I should gain</fav>
        <fav category="default" type="h" num="296">And can it be that I should gain</fav>
        <fav category="default" type="h" num="935">Around Thy grave, Lord Jesus</fav>
        <fav category="default" type="h" num="482">I am crucified with Christ</fav>
        <fav category="default" type="h" num="618">The old rugged cross</fav>
        <fav category="default" type="h" num="1006">There is a fountain filled with blood</fav>
        <fav category="default" type="lb" num="53">Worthy is the Lamb</fav>
        <fav category="default" type="h" num="1009">Would you be free from your burden of sin</fav>
    </favourites>
</user>
