<?xml version="1.0" encoding="utf-8"?>
<user xmlns="http://www.hymnal.net/user" version="1.0">
<firstname>rosinda</firstname>
<lastname>tafoya</lastname>
<email>jrtafoya@msn.com</email>
<password>$1$HXSl.K1d$/TdsMQnh3.GuhT/r5eJcK.</password>
<gender>F</gender>
<country>United States</country>
<ipaddress>71.105.191.15</ipaddress>
<createdate>2009-09-12 11:07:13</createdate>
<lastupdateddate>2009-09-15 19:18:30</lastupdateddate>
<lastlogindate></lastlogindate>
<failedlogincount></failedlogincount>
<favourites>
    </favourites>
</user>
