<?xml version="1.0" encoding="utf-8"?>
<user xmlns="http://www.hymnal.net/user" version="1.0">    <firstname>Holly</firstname>
    <lastname>Klass</lastname>
    <email>hklass@gmail.com</email>
    <password>6MnfBRCDZgX7LVyqFGJVvA%3D%3D</password>
    <gender>F</gender>
    <country>us</country>
    <ipaddress>98.215.80.101</ipaddress>
    <createdate>2010-03-06 23:20:06</createdate>
    <lastupdateddate>2010-03-06 23:21:02</lastupdateddate>
    <lastlogindate>2010-03-06 23:21:02</lastlogindate>
    <failedlogincount>0</failedlogincount>
    <favourites>
    </favourites>
</user>
