<?xml version="1.0" encoding="utf-8"?>
<!DOCTYPE html PUBLIC "-//W3C//DTD XHTML 1.0 Transitional//EN" "http://www.w3.org/TR/xhtml1/DTD/xhtml1-transitional.dtd">
<user>
<firstname>Alastair</firstname>
<lastname>Curry</lastname>
<email>john3v16@fsmail.net</email>
<password>$1$agu8/Xlc$OK3CXMlOjlQSeEmZ3Fgy81</password>
<gender>M</gender>
<country>United Kingdom</country>
<ipaddress>86.131.165.244</ipaddress>
<createdate>2009-01-25 18:16:55</createdate>
<lastupdateddate>2009-09-15 18:29:24</lastupdateddate>
<lastlogindate></lastlogindate>
<failedlogincount></failedlogincount>
<favourites>
    </favourites>
</user>
