<?xml version="1.0" encoding="utf-8"?>
<hymn xmlns="http://www.hymnal.net/hymn">
  <title>成為神的傑作</title>
  <index>true</index>
  <category>盼望與豫備</category>
  <numbers><chinese num="ts:921"/><english num="1321"/></numbers>
  <melody>| 0. 0 5/ | ._3 ._2/ ._2/( ._1/) 6/ | 5 6/ 5 5/ | 6/( 7/) ._1/ ._1/( ._2/) ._3/ (break) | ._2.( ._2) 5/ | ._3 7/ ._2/( ._1/) 6/ | 5 6/ 5 5/ | 6 6/ 7/( 6/) 5/ (break) | ._1.( ._1) ._3/ | ._3 3/ 3/( 4#/) 5#/ | 6 7/ ._1 ._3/ | ._2/( ._1/) 7/ 6/( 7/) 6/ (break) | 5.( 5) 5/ | ._3 7/ ._2/( ._1/) 6/ | 5 6/ 5 5/ | 6 6/ 7/( 6/) 5/ | ._1.( ._1) 0/ |</melody>
  <layout>
	<singingstanza>神 在 子 裏 成 為 肉 身， 乃 神 所 賜 宏 恩； 基 督 豐 富 享 受 不 盡， 供 應 全 備 常 新。 此 恩 浩 大， 超 人 能 度， 奇 妙， 難 盡 述 說； 否 則 滅 亡 之 子 如 我， 怎 能 成 神 傑 作？</singingstanza>
	<columns>2</columns>
  </layout>
  <music>
	<midiref type="h" num="960"/>
  </music>
  <lyrics>
	<stanza type="verse" number="1">神在子裏成為肉身，乃神所賜宏恩；
基督豐富享受不盡，供應全備常新。
此恩浩大，超人能度，奇妙，難盡述說；
否則滅亡之子如我，怎能成神傑作？</stanza>
	<stanza type="verse" number="2">受造之物受縛被囚，殷殷熱切等候，
神的眾子顯現時候，得享永遠自由。
我神定旨永遠深廣，就要完全明朗；
榮耀盼望如今隱藏，那時全得顯彰。</stanza>
	<stanza type="verse" number="3">番石榴樹代替蒺藜，松樹頂替荊棘；
和平掌權，戰爭消弭，咒詛再無蹤迹。
大山小山發聲歡呼，樹木拍掌鼓舞；
榮耀自由得以進入，當神眾子顯出。</stanza>
	<stanza type="verse" number="4">神的深恩細緻陶甄，每日作工我身；
分賜之工今雖隱藏，那日要顯無盡。
神的自己在我加添，神聖分賜無間；
受造萬有無不讚歎，當神傑作展現。</stanza>
	<stanza type="verse" number="5">得贖宇宙歡呼頌稱，神聖計畫成功！
千萬天使和聲歌頌，無邊榮耀之中。
惡者雖曾肆無忌憚，終如煙消雲散；
惟主智慧卓越超凡，配得永遠稱讚。</stanza>
	<stanza type="verse" number="6">為此我們欣然奉獻，配合主的心願，
接受祂的分賜、充滿，逐日讓祂擴展。
惟願今日生活點滴，盡是因典滴瀝；
是神自己加添我裏，那日光榮無比。</stanza>
  </lyrics>
</hymn>
