<?xml version="1.0" encoding="utf-8"?>
<user xmlns="http://www.hymnal.net/user" version="2.0">
  <roles>USER</roles>
  <firstname>Carrot</firstname>
  <lastname/>
  <email>rebecca_chiang0@yahoo.com.tw</email>
  <password>$2y$10$Cf1VCrIxEMfkSNJC.yGZae8F9EW.LpFCpG40LrsARwBH9sjA26rnW</password>
  <gender>F</gender>
  <country>Singapore</country>
  <ipaddress>182.55.242.238</ipaddress>
  <createdate>2014-05-27 15:13:48</createdate>
  <lastupdateddate>2016-08-07 04:23:27</lastupdateddate>
  <lastlogindate>2016-08-07 04:23:27</lastlogindate>
  <failedlogincount>0</failedlogincount>
  <favourites>
    <fav category="default" type="ns" num="378">A Life of No Regrets</fav>
    <fav category="default" type="ns" num="309">A Noble Deed</fav>
    <fav category="default" type="ns" num="398">A Person of Life</fav>
    <fav category="default" type="ns" num="6">A divine, romantic story</fav>
    <fav category="default" type="ns" num="134">A higher view</fav>
    <fav category="default" type="h" num="1343">A new commandment</fav>
    <fav category="default" type="h" num="43">Abba, Father, we approach Thee</fav>
    <fav category="default" type="ns" num="530">Above the Waste and Emptiness</fav>
    <fav category="default" type="lb" num="29">As virgins we must be wise and pure</fav>
    <fav category="default" type="h" num="224">As we're sharing of the cup</fav>
    <fav category="default" type="ns" num="435">Back in My Father's House Again!</fav>
    <fav category="default" type="ns" num="339">But holding to truth in love</fav>
    <fav category="default" type="ns" num="506">Choose to Be an Overcomer</fav>
    <fav category="default" type="h" num="507">Christ liveth in me</fav>
    <fav category="default" type="ns" num="375">Come Forward</fav>
    <fav category="default" type="ns" num="285">Come, Lord Jesus</fav>
    <fav category="default" type="ns" num="108">Crazy lovers of Jesus</fav>
    <fav category="default" type="ns" num="51">Create in me a clean heart, O God</fav>
    <fav category="default" type="h" num="62">Dear Lord Jesus, we adore Thee</fav>
    <fav category="default" type="h" num="222">Dear Lord, we thank Thee for this bread</fav>
    <fav category="default" type="ns" num="97">Dearest Lord, You've called us here</fav>
    <fav category="default" type="lb" num="82">Divine romance</fav>
    <fav category="default" type="ns" num="164">Do you know what you were made for</fav>
    <fav category="default" type="h" num="82">Down from His glory</fav>
    <fav category="default" type="ns" num="302">Draw me, dear Lord</fav>
    <fav category="default" type="h" num="1151">Drink! A river pure and clear that's flowing from the throne</fav>
    <fav category="default" type="h" num="1108">Eat the bread, ye people of the Lord</fav>
    <fav category="default" type="ns" num="105">Fallen, that's the way we all begin</fav>
    <fav category="default" type="h" num="1081">Father God, Thou art the source of life</fav>
    <fav category="default" type="ns" num="352">For her</fav>
    <fav category="default" type="h" num="840">Freed from self and Adam's nature</fav>
    <fav category="default" type="h" num="774b">From every stormy wind that blows (Alternate Tune)</fav>
    <fav category="default" type="ns" num="168">From the time I spoke Your name</fav>
    <fav category="default" type="ns" num="160">Give Yourself to Love the Lord</fav>
    <fav category="default" type="h" num="1025">Give up the world, Christ to obtain</fav>
    <fav category="default" type="h" num="1">Glory be to God</fav>
    <fav category="default" type="h" num="7">Glory, glory to the Father</fav>
    <fav category="default" type="ns" num="3">God has a dream</fav>
    <fav category="default" type="ns" num="28">God has called us for His purpose</fav>
    <fav category="default" type="nt" num="720">God hath not promised skies always blue</fav>
    <fav category="default" type="lb" num="11">God is love</fav>
    <fav category="default" type="ns" num="48">God wants someone to love Him</fav>
    <fav category="default" type="h" num="947">God's Kingdom today is a real exercise</fav>
    <fav category="default" type="ns" num="181">God's economy and His eternal plan</fav>
    <fav category="default" type="ns" num="319">God's economy is His plan to dispense Himself</fav>
    <fav category="default" type="h" num="5">God, our Father, we adore Thee</fav>
    <fav category="default" type="h" num="26">God, we praise Thee for Thy mercy</fav>
    <fav category="default" type="h" num="1335">Great is the Lord, and greatly to be praised</fav>
    <fav category="default" type="nt" num="437">Hast thou heard Him, seen Him, known Him?</fav>
    <fav category="default" type="ns" num="146">He who sows unto his own flesh</fav>
    <fav category="default" type="ns" num="53">He's my God</fav>
    <fav category="default" type="h" num="18">How faithful and trustworthy too</fav>
    <fav category="default" type="h" num="1086">How we love the glorious name</fav>
    <fav category="default" type="ns" num="133">I Love My Master</fav>
    <fav category="default" type="ns" num="167">I always knew deep down in me</fav>
    <fav category="default" type="ns" num="283">I am crucified with Christ</fav>
    <fav category="default" type="h" num="877">I dare not be defeated</fav>
    <fav category="default" type="lb" num="51">I do not know where they have laid Him</fav>
    <fav category="default" type="ns" num="65">I love God because...</fav>
    <fav category="default" type="h" num="1154">I love Thee, Jesus</fav>
    <fav category="default" type="ns" num="82">I once was dead&amp;mdash;dead in my sins</fav>
    <fav category="default" type="ns" num="190">I want to be filled with the Triune God</fav>
    <fav category="default" type="ns" num="131">I'm gonna praise God unceasingly</fav>
    <fav category="default" type="ns" num="117">I'm thankful that God has placed me</fav>
    <fav category="default" type="ns" num="98">I'm walking down the road</fav>
    <fav category="default" type="h" num="210">I've found a friend in Jesus, He's everything to me</fav>
    <fav category="default" type="h" num="510">I've found the One of peerless worth</fav>
    <fav category="default" type="ns" num="224">I've given up the world because</fav>
    <fav category="default" type="ns" num="37">I've got a river of life flowing within me</fav>
    <fav category="default" type="c" num="60">I've got the joy, joy, joy, joy</fav>
    <fav category="default" type="nt" num="1079">If I gained the world, but lost the Savior</fav>
    <fav category="default" type="ns" num="191">If you are hungry, come to the feast</fav>
    <fav category="default" type="ns" num="163">If you wish to find the Lord</fav>
    <fav category="default" type="ns" num="158">Immersed in Thy love</fav>
    <fav category="default" type="h" num="23">In all Thy wisdom, Father God</fav>
    <fav category="default" type="h" num="203">In the bosom of the Father</fav>
    <fav category="default" type="ns" num="315">In this godless age</fav>
    <fav category="default" type="h" num="154">It passeth knowledge, that dear love of Thine</fav>
    <fav category="default" type="ns" num="188">It's the life, life, life</fav>
    <fav category="default" type="ns" num="118">Jesus Lord, You're our first love</fav>
    <fav category="default" type="ns" num="351">Jesus Lord, my best love Thou art</fav>
    <fav category="default" type="ns" num="74">Jesus, O living Word of God</fav>
    <fav category="default" type="lb" num="14">Just one touch</fav>
    <fav category="default" type="ns" num="19">Let me love and not be requited</fav>
    <fav category="default" type="lb" num="1">Let me stand behind You, Lord</fav>
    <fav category="default" type="lb" num="27">Let's go on</fav>
    <fav category="default" type="ns" num="110">Life's too short</fav>
    <fav category="default" type="ns" num="471">Living Christ, Our Victory</fav>
    <fav category="default" type="h" num="132">Lo! in heaven Jesus sitting</fav>
    <fav category="default" type="h" num="1101">Lo, the kingdom of the world is now</fav>
    <fav category="default" type="h" num="171">Lord Jesus Christ, our heart feels sweet</fav>
    <fav category="default" type="ns" num="231">Lord Jesus, I love You, You're my all</fav>
    <fav category="default" type="ns" num="78">Lord Jesus, You're lovely</fav>
    <fav category="default" type="ns" num="40">Lord Jesus, draw me</fav>
    <fav category="default" type="lb" num="65">Lord, I love You more and more each day</fav>
    <fav category="default" type="ns" num="42">Lord, I love You more today</fav>
    <fav category="default" type="ns" num="129">Lord, You are Beloved</fav>
    <fav category="default" type="ns" num="46">Lord, You love me so immensely</fav>
    <fav category="default" type="ns" num="214">Lord, grant me today's supply of grace</fav>
    <fav category="default" type="ns" num="130">Lord, how I thank You</fav>
    <fav category="default" type="lb" num="40">Lord, how long</fav>
    <fav category="default" type="lb" num="52">Lord, keep my heart always true to You</fav>
    <fav category="default" type="ns" num="209">Lord, now I see</fav>
    <fav category="default" type="ns" num="175">Lord, there's always been one person</fav>
    <fav category="default" type="h" num="221">Lord, we thank Thee for the table</fav>
    <fav category="default" type="ns" num="23">Lovers of Christ</fav>
    <fav category="default" type="h" num="1299">Man's Creator has a purpose</fav>
    <fav category="default" type="nt" num="1299">Man's Creator has a purpose</fav>
    <fav category="default" type="h" num="322">Many weary years I vainly sought a spring</fav>
    <fav category="default" type="ns" num="99">Mary poured out her love offering</fav>
    <fav category="default" type="ns" num="169">Morning dawn had arisen</fav>
    <fav category="default" type="h" num="17">My Father God, when on Thy vast creation</fav>
    <fav category="default" type="nt" num="600">My God, my Portion</fav>
    <fav category="default" type="h" num="960">My King will soon come back again</fav>
    <fav category="default" type="nt" num="165">My song shall be of Jesus</fav>
    <fav category="default" type="ns" num="199">Nearer each day</fav>
    <fav category="default" type="ns" num="205">Nothing can content me more</fav>
    <fav category="default" type="ns" num="114">Nothing's quite so precious</fav>
    <fav category="default" type="ns" num="103">Now Christ is the life-giving Spirit</fav>
    <fav category="default" type="lb" num="70">Now from my heart comes</fav>
    <fav category="default" type="ns" num="186">Now the Lord is the Spirit&amp;mdash;that's how</fav>
    <fav category="default" type="lb" num="21">O God of glory</fav>
    <fav category="default" type="h" num="12">O God, Thou art the source of life</fav>
    <fav category="default" type="h" num="1293">O I'm a man</fav>
    <fav category="default" type="h" num="1110">O Jesus Lord, when present at Thy table</fav>
    <fav category="default" type="h" num="976">O Lord Jesus, Thy redeemed ones</fav>
    <fav category="default" type="ns" num="25">O Lord, I love You, I really love You</fav>
    <fav category="default" type="h" num="190">O Lord, as we consider Thee</fav>
    <fav category="default" type="h" num="255">O Lord, breathe Thy Spirit on me</fav>
    <fav category="default" type="h" num="1097">O Lord, our Lord, how excellent</fav>
    <fav category="default" type="ns" num="141">O glorious divine love</fav>
    <fav category="default" type="h" num="152">O how deep and how far-reaching</fav>
    <fav category="default" type="h" num="602">O how glorious! O how holy</fav>
    <fav category="default" type="ns" num="104">O that Christ may make His home</fav>
    <fav category="default" type="ns" num="26">O the joy of having nothing</fav>
    <fav category="default" type="ns" num="27">Oh! the joy</fav>
    <fav category="default" type="h" num="223">On the table of Thy love</fav>
    <fav category="default" type="c" num="53">Once I thought the love of God</fav>
    <fav category="default" type="ns" num="80">Our Christ is so enjoyable</fav>
    <fav category="default" type="h" num="16">Our Father, as the evergreen</fav>
    <fav category="default" type="h" num="925">Outreach of the glorious gospel</fav>
    <fav category="default" type="h" num="124">Praise Him! praise Him! Christ is Victor</fav>
    <fav category="default" type="h" num="235">Praise Him! praise Him! Jesus, our blessed Redeemer</fav>
    <fav category="default" type="ns" num="225">Praise the Lord! The God of glory</fav>
    <fav category="default" type="lb" num="41">Pursue Him and know Him</fav>
    <fav category="default" type="h" num="1248">Recall how David swore</fav>
    <fav category="default" type="lb" num="22">Shepherd, receive man</fav>
    <fav category="default" type="ns" num="192">Some, these days, would tell us that our Jesus is not food</fav>
    <fav category="default" type="lb" num="69">Someone</fav>
    <fav category="default" type="ns" num="219">Sometimes we're caught in a world full of baits</fav>
    <fav category="default" type="ns" num="396">Take me Lord, and fill me with Your dear Self</fav>
    <fav category="default" type="ns" num="30">Take time to absorb Him</fav>
    <fav category="default" type="ns" num="135">Thank You, Lord Jesus, for dying for me</fav>
    <fav category="default" type="lb" num="76">That's Why I Love Him</fav>
    <fav category="default" type="ns" num="58">The Bible is God's breath</fav>
    <fav category="default" type="lb" num="5">The Bible is a romance</fav>
    <fav category="default" type="h" num="824">The Church is Christ's own Body</fav>
    <fav category="default" type="ns" num="107">The best love for the Lord</fav>
    <fav category="default" type="ns" num="412">The church is the building up</fav>
    <fav category="default" type="ns" num="102">The gift of righteousness</fav>
    <fav category="default" type="lb" num="67">The love of Christ is now constraining me</fav>
    <fav category="default" type="lb" num="42">The love of God and the grace of Christ</fav>
    <fav category="default" type="h" num="28">The love of God is greater far</fav>
    <fav category="default" type="ns" num="290">The song to my Beloved</fav>
    <fav category="default" type="ns" num="287">There are Times</fav>
    <fav category="default" type="ns" num="111">There's a gospel of today</fav>
    <fav category="default" type="ns" num="217">There's a life that's deeper than our mind</fav>
    <fav category="default" type="ns" num="64">There's a man who died to set us free</fav>
    <fav category="default" type="h" num="1341">Therefore the redeemed of the Lord shall return</fav>
    <fav category="default" type="h" num="1340">Therefore with joy shall ye draw water</fav>
    <fav category="default" type="ns" num="383">These things says the Holy One</fav>
    <fav category="default" type="h" num="121">Thine be the glory, risen, conqu'ring Son</fav>
    <fav category="default" type="h" num="13">Thou art love and Thou art light, Lord</fav>
    <fav category="default" type="ns" num="301">Thou art my Beloved, the most lovely Beloved</fav>
    <fav category="default" type="h" num="386">Thou my everlasting Portion</fav>
    <fav category="default" type="ns" num="246">Though I love You, Lord</fav>
    <fav category="default" type="ns" num="292">Though the world may promise me more</fav>
    <fav category="default" type="h" num="227">Through the bread and cup, Lord Jesus</fav>
    <fav category="default" type="h" num="1152">To Jesus every day we find our hearts are closer drawn</fav>
    <fav category="default" type="ns" num="143">To You, dear Lord</fav>
    <fav category="default" type="ns" num="517">Treasure in Earthen Vessels</fav>
    <fav category="default" type="h" num="582">Trust and obey</fav>
    <fav category="default" type="h" num="41">We are never weary singing our eternal song</fav>
    <fav category="default" type="ns" num="88">We are one in Christ</fav>
    <fav category="default" type="ns" num="322">We have found a simple way</fav>
    <fav category="default" type="h" num="1178">We have seen Christ is reality</fav>
    <fav category="default" type="h" num="40">We praise Thee, O God</fav>
    <fav category="default" type="h" num="1141">We will sing to the Lord with our spirit</fav>
    <fav category="default" type="h" num="1107">We're gathered here, O Lord, as Thy one Body</fav>
    <fav category="default" type="h" num="848">What a blessing, what a priv'lege</fav>
    <fav category="default" type="lb" num="66">What made You die for me</fav>
    <fav category="default" type="ns" num="151">What miracle! What mystery!</fav>
    <fav category="default" type="ns" num="138">What things were gains to me</fav>
    <fav category="default" type="h" num="8773">When I've run the race before me</fav>
    <fav category="default" type="h" num="220">When on Thy table, Lord, we gaze</fav>
    <fav category="default" type="ns" num="49">Whispers from above</fav>
    <fav category="default" type="ts" num="337">一件美事</fav>
    <fav category="default" type="ch" num="443">何等榮耀何等神聖</fav>
    <fav category="default" type="ch" num="467">你怎沒有傷痕</fav>
    <fav category="default" type="ts" num="762">同活在主身體中</fav>
    <fav category="default" type="ts" num="105">基督是那賜生命的靈</fav>
    <fav category="default" type="ts" num="329">惟見榮耀裡的基督</fav>
    <fav category="default" type="ts" num="466">新的黎明，新的復興</fav>
    <fav category="default" type="ns" num="517c">瓦器裏有寶貝</fav>
    <fav category="default" type="ts" num="425">與主相見在清晨</fav>
    <fav category="default" type="ts" num="428">讓我愛</fav>
  </favourites>
</user>
