<?xml version="1.0" encoding="utf-8"?>
<hymn xmlns="http://www.hymnal.net/hymn">
  <title>O Lord, with Thy Holy Ghost</title>
  <index>true</index>
  <category>Fulness of the Spirit&amp;mdash;The Filling</category>
  <creators>
    <author biodate="1869-1930" biolink="en.wikipedia.org/wiki/Margaret_E._Barber">Margaret E. Barber, adapted</author>
    <composer biodate="1842-1914" biolink="">Robert Jackson</composer>
  </creators>
  <meter>7.7.7.7.7.7.</meter>
  <hymncode>3332344444432555</hymncode>
  <key>D Major</key>
  <time>3/4</time>
  <tempo>100</tempo>
  <chords>| C - - | Am - - | Dm - - | Dm/F - - | G7 - - | G/B - - | C/E - G/D | C - - | G - - | Am - - | Dm/F - A | Dm - - | E - - | Am - - | Dm - - | E - - | C - - | C7 - - | F - C/E | F - - | F/A - - | C/G - F/A | C/G - G7 | C - - |</chords>
  <melody>| 3 - 3 | 3( 2) 3 | 4 - 4 | 4 - - | 4 - 4 | 4( 3) 2 | 5 - 5 | 5 - - (break) | 5( 6) 7 | ._1 - 1 | 2 - 3 | 4 - - | 3 - 2 | 1 - 1 | 2 - 1 | 7_. - - (break) | 1 - 1 | 1( 2) 3 | 4 - 5 | 6 - - | ._1( 7) 6 | 5( 3) 4 | 3 - 2 | 1 - - |</melody>
  <layout>
    <singingstanza>O Lord, with Thy Ho -- ly Ghost, Fill me to the ut -- ter -- most; Let my life Thy chan -- nel be, Just a chan -- nel, Lord, for Thee; Through me all Thy rich -- es pour, Give me ev -- er more and more.</singingstanza>
  </layout>
  <links>
    <link type="group">hymnal-subj094.xml</link>
  </links>
  <music>
    <midi location="h" length="35">e0269_i.mid</midi>
  </music>
  <lyrics>
    <stanza type="verse" number="1">O Lord, with Thy Holy Ghost,
Fill me to the uttermost;
Let my life Thy channel be,
Just a channel, Lord, for Thee;
Through me all Thy riches pour,
Give me ever more and more.</stanza>
    <stanza type="verse" number="2">O Lord, with Thy Holy Ghost,
Fill me to the uttermost;
Be it unto me, O Lord,
Now, according to Thy word;
Let the life of Jesus be,
Ever filling, even me.</stanza>
    <stanza type="verse" number="3">O Lord, with Thy Holy Ghost,
Fill me to the uttermost;
Cleansed and holy, pure and clean,
Let the life of Christ be seen;
Hold o'er me Thy gracious sway,
Every hour of every day.</stanza>
    <stanza type="verse" number="4">O Lord, with Thy Holy Ghost,
Fill me to the uttermost;
For Thy love, Thy light, Thy grace,
Just a channel all my days;
Till my Savior's face I see,
Fill me, Lord, fill even me.</stanza>
  </lyrics>
</hymn>
