<?xml version="1.0" encoding="utf-8"?>
<!DOCTYPE html PUBLIC "-//W3C//DTD XHTML 1.0 Transitional//EN" "http://www.w3.org/TR/xhtml1/DTD/xhtml1-transitional.dtd">
<user>
    <firstname>林志斌</firstname>
    <lastname></lastname>
    <email>apple8111588@yahoo.com.tw</email>
    <password>krIlWQY1ftwpNifrNYOeYA%3D%3D</password>
    <gender></gender>
    <country>Taiwan</country>
    <ipaddress>61.231.4.47</ipaddress>
    <createdate>2013-09-25 06:50:59</createdate>
    <lastupdateddate>2013-09-25 07:05:34</lastupdateddate>
    <lastlogindate>2013-09-25 06:50:59</lastlogindate>
    <failedlogincount>0</failedlogincount>
    <favourites>
    </favourites>
</user>
