<?xml version="1.0" encoding="utf-8"?>
<user xmlns="http://www.hymnal.net/user" version="1.0">
    <firstname>uttextcic</firstname>
    <lastname></lastname>
    <email>babala1648@need-mail.com</email>
    <password>36JTprxP7P6%2B8PmvXyLbdQ%3D%3D</password>
    <gender></gender>
    <country>Bangladesh</country>
    <ipaddress>58.22.21.243</ipaddress>
    <createdate>2013-04-30 17:18:40</createdate>
    <lastupdateddate>2013-04-30 17:18:51</lastupdateddate>
    <lastlogindate>2013-04-30 17:18:51</lastlogindate>
    <failedlogincount>0</failedlogincount>
    <favourites>
    </favourites>
</user>
