<?xml version="1.0" encoding="utf-8"?>
<user xmlns="http://www.hymnal.net/user" version="1.0">
<firstname>Lance</firstname>
<lastname>OConner</lastname>
<email>lanceoconner@gmail.com</email>
<password>$1$qT/k/gVF$Q5no/IYSJGLCZb8V3mPMX0</password>
<gender>M</gender>
<country>United States</country>
<ipaddress>24.210.151.194</ipaddress>
<createdate>2009-03-23 06:32:12</createdate>
<lastupdateddate>2009-09-15 18:29:41</lastupdateddate>
<lastlogindate></lastlogindate>
<failedlogincount></failedlogincount>
<favourites>
    </favourites>
</user>
