<?xml version="1.0" encoding="utf-8"?>
<user xmlns="http://www.hymnal.net/user" version="1.0">    <firstname>Franklin</firstname>
    <lastname>Foulen</lastname>
    <email>ffoulen@msn.com</email>
    <password>RdxEhcrfJ4rCDhgNQWvXpQ%3D%3D</password>
    <gender>M</gender>
    <country>us</country>
    <ipaddress>173.77.127.109</ipaddress>
    <createdate>2009-11-22 22:34:06</createdate>
    <lastupdateddate>2009-11-22 23:50:57</lastupdateddate>
    <lastlogindate>2009-11-22 23:38:55</lastlogindate>
    <failedlogincount>0</failedlogincount>
    <favourites>
        <fav category="default" type="h" num="308">Blessed assurance</fav>
    </favourites>
</user>
