<?xml version="1.0" encoding="utf-8"?>
<hymn xmlns="http://www.hymnal.net/hymn">
  <title>Bago magbukang-liwayway</title>
  <index>true</index>
  <category>PAGDARANAS KAY KRISTO&amp;mdash;PAKIKISALAMUHA SA KANYA</category>
  <numbers><cebuano num="554"/><chinese num="417"/><english num="554"/><german num="554"/><korean num="417"/><portuguese num="280"/><russian num="317"/><spanish num="259"/><tagalog num="554"/></numbers>
  <creators>
	<author biodate="1905-1997" biolink="www.witnesslee.org">Translated from Witness Lee</author>
  </creators>
  <melody>| 0. 0 5_./ | 5_./ 3_./ 4_./ 5_./ 1/ 2/ | 3.( 3/) 2/ 1/ | 1 1/ 2/ 1/ 6_./ (break) | 1.( 5_.) 7_.//( 1//) | 2 2/ 7_. 6_.// 7_.// | 1 2/ 3 3/ | 2 3/ 2 1/ (break) | 7_. 1/ (.2/ (Chorus) (.3./( 2//) | 1 1/ 1/ 7_./ 6_./ | 7_. 7_./ 7_. 5_.// 5_.// | 4 4// 4// 4/( 3/) 2#/ (break) | 3.( 3) 1//( 2//) | 3 3/ 2 7_./ | 1 1/ (.1 6_./ | 5_../ 1// 1/ 7_./( 2./) 2// | 1.( 1) 0/ |</melody>
  <music>
	<midiref type="h" num="501"/>
  </music>
  <lyrics>
	<stanza type="verse" number="1">Bago magbukang-liwayway
Sa Kanyang presensya'y lumapit;
Ang Kanyang mukha'y aking namasdan,
Liwanag ay sumapit.
Sa 'kin sinalita't 'pinahayag
Lahat ng yaman Niya ngayon;
Buong lugod ako'y bumahagi,
Napawi aking gutom.</stanza>
	<stanza type="verse" number="2">'Spiritu'y nagsalamuha
Sa pamam'gitan ng Salita;
Bukal ng buhay sa aking puso,
Dala'y lakas, biyaya.
Sa 'kin sinalita't 'pinahayag
Yaman Niya'y ipinabatid;
Kaya sa Kanya ako'y uminom,
Uhaw ko ay napatid.</stanza>
	<stanza type="verse" number="3">Magiliw makitungo Siya
Sa presensiya Niya'y may ligaya;
Ako'y pinuspusan, tinustusan
Ng lahat Niyang esensiya.
Sa 'kin sinalita't 'pinahayag
Ang Kanyang yaman nang lubos;
Ako ay nagtamasa sa Kanya,
Sulirani'y natapos.</stanza>
  </lyrics>
</hymn>
