<?xml version="1.0" encoding="utf-8"?>
<hymn xmlns="http://www.hymnal.net/hymn">
  <title>Bundok sabihan: "Sa dagat matapon ka!"</title>
  <index>true</index>
  <category>PANALANGIN&amp;mdash;SA PANANAMPALATAYA</category>
  <numbers><chinese num="560"/><english num="777"/><korean num="560"/><tagalog num="777"/></numbers>
  <creators>
    <author biodate="" biolink="">Streams in the Desert, adapted</author>
  </creators>
  <music>
    <midiref type="h" num="777"/>
  </music>
  <lyrics>
    <stanza type="verse" number="1">Bundok sabihan: "Sa dagat matapon ka!"
Sa iyo'y matutupad kung di ka magduda;
Manalig sa Salita Niya.
Bundok mo'y iyong utusan na!</stanza>
    <stanza type="verse" number="2">Sa dugo'y binili, kamtan pribileh'yo,
Sa Trinidad 'ugpong epektibo;
Sumunod sa Salita Niya.
Bundok mo'y iyong utusan na!</stanza>
    <stanza type="verse" number="3">Sarili, pighati, sala'y pinasan Niya,
Nais Niya'y natug'nan, at napalaya ka;
Umasa sa Salita Niya.
Bundok mo'y iyong utusan na!</stanza>
    <stanza type="verse" number="4">Patuloy ang dasal, moog palibutan,
Bago pa bumagsak, Poon papurihan;
Panatag, maniwala ka.
Bundok mo'y iyong utusan na!</stanza>
    <stanza type="verse" number="5">Mga pintong tanso't mga barang bakal,
Mapasubo ng nananalig na kawal;
Kaaway ibale-wala.
Bundok mo'y iyong utusan na!</stanza>
    <stanza type="verse" number="6">Gamitin Kanyang pananampalataya,
Tungkod gumagawa ng kamangha-mangha;
Alisin lahat mong duda.
Bundok mo'y iyong utusan na!</stanza>
  </lyrics>
</hymn>
