<?xml version="1.0" encoding="utf-8"?>
<hymn xmlns="http://www.hymnal.net/hymn">
  <title>В моём духе, внутри, – вечной жизни родник</title>
  <index>true</index>
  <category>ПЕРЕЖИВАНИЕ БОГА&amp;mdash;КАК ЖИЗНИ</category>
  <numbers><cebuano num="1191"/><chinese num="ts:410"/><english num="1191"/><german num="1191"/><portuguese num="310"/><russian num="117"/><spanish num="222"/><tagalog num="1191"/></numbers>
  <creators>
	<author biodate="" biolink="" fullname="Ron Kangas">Translated from R. K.</author>
  </creators>
  <melody>| 0 - 3/ 4/ | 5. 4#/ 6 | 5 - 5/ 5/ | 6. 5#/ 7 | 6 - 6 | 7. 6/ 5 | 4 5 4 | 3( - - (break) | 3) - 3/ 4/ | 5. 4#/ 6 | 5 - 5/ 5/ | 6. 5#/ 7 | 6 - 6/ 6/ | 7. 6/ 5 | ._4 ._3 ._2 | ._1( - - (break) | ._1) - (Chorus) 7/ ._1/ | ._2. ._2/ ._2 | ._2 ._1 7 | ._1( - - | ._1) - ._1/ 7/ | 6. 6/ 6 | ._1 7 6 | 5( - - (break) | 5) - 5/ ._1/ | ._3. ._3/ ._3 | ._3 ._4 ._3 | 6( - - | 6) - ._4/ ._4/ | ._3. ._2/ ._1 | 5 7 ._2 | ._1( - - | ._1) - 0 |</melody>
  <layout>
	<singingstanza>В_мо -- ём ду -- хе, вну -- три,_– веч -- ной жиз -- ни род -- ник: Здесь Бог Три -- е -- ди -- ный те -- чёт.  Бог О -- тец есть ис -- ток, рус -- ло_– Сын, Сам Хрис -- тос, И о -- биль -- но мне Дух жизнь да -- ёт. О, как до -- рог, Гос -- подь, Твой по -- ток!  Ду -- шу -- жизнь я от -- верг на -- ко -- нец!  У -- губ -- ляй э -- тот чис -- тый по -- ток И, при -- дя, дай мне жизнь как ве -- нец.</singingstanza>
  </layout>
  <music>
	<midiref type="h" num="618"/>
  </music>
  <lyrics>
	<stanza type="verse" number="1">В моём духе, внутри, – вечной жизни родник:
Здесь Бог Триединый течёт.
Бог Отец есть исток, русло – Сын, Сам Христос,
И обильно мне Дух жизнь даёт.</stanza>
	<stanza type="chorus" number="">О, как дорог, Господь, Твой поток!
Душу-жизнь я отверг наконец!
Угубляй этот чистый поток
И, придя, дай мне жизнь как венец.</stanza>
	<stanza type="verse" number="2">Иисус, Пастырь мой, мне дарует покой
И к тихим Он водам ведёт.
Прекратил я борьбу и свою суету;
В том потоке – блаженство моё.</stanza>
	<stanza type="verse" number="3">Я по зову Его во святое святых
Пришёл пред лицом Его жить.
Аллилуйя, Иисус ободряет меня:
«Пребудь во Мне – ты ветвь Лозы».</stanza>
  </lyrics>
</hymn>
