<?xml version="1.0" encoding="utf-8"?>
<hymn xmlns="http://www.hymnal.net/hymn">
  <title>В Духе передаётся Бог</title>
  <index>true</index>
  <category>ПЕРЕЖИВАНИЕ БОГА&amp;mdash;ПОСРЕДСТВОМ ДУХА КАК ПЕРЕДАЧИ</category>
  <numbers><cebuano num="610"/><chinese num="452"/><english num="610"/><german num="610"/><korean num="452"/><portuguese num="317"/><russian num="321"/><spanish num="289"/><tagalog num="610"/></numbers>
  <creators>
	<author biodate="1905-1997" biolink="www.witnesslee.org">Translated from Witness Lee</author>
  </creators>
  <melody>| 1 1 1 | 1( 7_.) 1 | 2( 3) 2 | 1 - - (break) | 3 3 3 | 3( 2) 3 | 5( 4) 3 | 2 - - (break) | 2 2 3 | 4 - 2 | 3 - 4 | 5 - - (break) | 6 6 6 | 5 - 3 | 4( 3) 2 | 1 - - |</melody>
  <music>
	<midiref type="h" num="374"/>
  </music>
  <lyrics>
	<stanza type="verse" number="1">В Духе передаётся Бог.
В Духе Святом Он входит в нас.
Бога в Христе мы можем так
В Духе переживать сейчас.</stanza>
	<stanza type="verse" number="2">Бог как Отец – всему исток;
Бога Отца являет Сын,
Бог входит в нас как Дух, чтоб мы
Как всем во всём владели Им.</stanza>
	<stanza type="verse" number="3">В свете сокрытого Отца
Полностью людям Сын открыл.
Дух нам Его передаёт,
Чтоб изнутри Он познан был.</stanza>
	<stanza type="verse" number="4">Бог триедин, и Он – одно,
Сын есть в Отце, Сын – Дух сейчас.
Бог как Отец, и Сын, и Дух
С нами един, сейчас Он в нас.</stanza>
	<stanza type="verse" number="5">Сын – воплощение Отца
И выражение Его;
Сына действительность есть Дух,
Ей мы владеем чрез Него.</stanza>
	<stanza type="verse" number="6">Хотим познать любовь Отца
В Сыне Его как благодать
Через общенье Духа мы,
Чтоб Богу нашей долей стать.</stanza>
  </lyrics>
</hymn>
