<?xml version="1.0" encoding="utf-8"?>
<hymn xmlns="http://www.hymnal.net/hymn">
  <title>Как небес сияет царство</title>
  <index>true</index>
  <category>ЦАРСТВО&amp;mdash;ЕГО ПРОЯВЛЕНИЕ</category>
  <numbers><cebuano num="946"/><chinese num="749"/><english num="946"/><korean num="749"/><portuguese num="475"/></numbers>
  <creators>
    <author biodate="1905-1997" biolink="www.witnesslee.org">Translated from Witness Lee</author>
  </creators>
  <melody>| 5_. - 5_. | 6_. - 6_. | 5_.( 1) 3 | 3 - 2 | 1 - 7_. | 6_. - 5_. | 5_.( 7_.) 6_. | 5_. - - (break) | 5_. - 5_. | 6_. - 6_. | 5_.( 1) 3 | 3 - 2 | 1 - 2 | 3( 4) 2 | 1 - 7_. | 1 - - (break) | 3 - 3 | 3( 1) 3 | 4( 3) 2 | 3 - 3 | 5 - 5 | 5( 3) 5 | 6( 5) 4# | 5 - - (break) | 6 - 4 | 5 - 3 | 5( 4) 3 | 3 - 2 | 1 - 2 | 3( 4) 2 | 1 - 7_. | 1 - - |</melody>
  <music>
    <midiref type="h" num="741"/>
  </music>
  <lyrics>
    <stanza type="verse" number="1">Как небес сияет царство!
В славе явлено оно!
На престол посажен Богом
Наш Господь и Царь его.
Он, придя однажды в плоти,
Был людьми уничижён;
Чтобы царства план исполнить,
В славе вновь приходит Он.</stanza>
    <stanza type="verse" number="2">К Богу вечному за царством
Он отправился давно
И теперь приходит с царством
И сиянием его.
Он тот ''Камень'', что народы
Сокрушает в пыль и прах;
Становясь ''горой великой'',
Он являет царство так.</stanza>
    <stanza type="verse" number="3">Бог с Его Христом владеют
Всеми царствами земли;
Их всевластное правленье
Ей несёт покой и мир.
Меж народами не будет
Ни раздора, ни войны;
Знаньем Бога будут полны,
Как моря – водой, они.</stanza>
    <stanza type="verse" number="4">В царстве будут править в славе
Победители с Христом,
А Израиля остаток
Обретёт священство в нём.
Под правленьем их – народы,
Будут их учить они,
И воссоздано творенье
Будет в славе в эти дни.</stanza>
    <stanza type="verse" number="5">Сатана в изгнанье будет,
Власть утратит на земле,
И Христос Своим правленьем
Принесёт блаженство ей.
Всё покорно будет воле
И могуществу Христа;
Как Глава и Центр славный
Он исполнит Божий план.</stanza>
  </lyrics>
</hymn>
