<?xml version="1.0" encoding="utf-8"?>
<user xmlns="http://www.hymnal.net/user" version="1.0">
  <roles/>
  <firstname>Sean</firstname>
  <lastname>Clemo</lastname>
  <email>sean.clemo@gmail.com</email>
  <password>c2GpLiwqeStVpvH6CaMBAQ%3D%3D</password>
  <gender/>
  <country>United Kingdom</country>
  <ipaddress>86.10.180.27</ipaddress>
  <createdate>2013-06-21 12:23:52</createdate>
  <lastupdateddate>2014-08-25 12:51:41</lastupdateddate>
  <lastlogindate>2014-08-25 12:51:41</lastlogindate>
  <failedlogincount>1</failedlogincount>
  <favourites>
  </favourites>
</user>
