<?xml version="1.0" encoding="utf-8"?>
<user xmlns="http://www.hymnal.net/user" version="2.0">
  <roles>USER</roles>
  <firstname>Debra</firstname>
  <lastname>rogers</lastname>
  <email>rogersdd@earthlink.net</email>
  <password>$2y$10$aNW1mInEM9yYcgJ314nbve/cfVPJIjJ6VehA.Ly8X8wpHX1FkdOCu</password>
  <gender/>
  <country>us</country>
  <ipaddress>97.103.201.20</ipaddress>
  <createdate>2014-06-18 02:57:52</createdate>
  <lastupdateddate>2014-06-18 03:00:08</lastupdateddate>
  <lastlogindate>2014-06-18 03:00:08</lastlogindate>
  <failedlogincount>0</failedlogincount>
  <favourites>
  </favourites>
</user>
