<?xml version="1.0" encoding="utf-8"?>
<user xmlns="http://www.hymnal.net/user" version="1.0">
    <firstname>Gilbert</firstname>
    <lastname>Dawson</lastname>
    <email>gilbertksdawson@gmail.com</email>
    <password>4GHx%2FRfcAYc0XANKqkLI4A%3D%3D</password>
    <gender></gender>
    <country>India</country>
    <ipaddress>14.99.208.205</ipaddress>
    <createdate>2013-04-21 12:46:04</createdate>
    <lastupdateddate>2013-04-21 12:46:04</lastupdateddate>
    <lastlogindate>2013-04-21 12:46:04</lastlogindate>
    <failedlogincount>0</failedlogincount>
    <favourites>
    </favourites>
</user>
