<?xml version="1.0" encoding="utf-8"?>
<hymn xmlns="http://www.hymnal.net/hymn">
  <title>Ginoo's paghandom namo</title>
  <index>true</index>
  <category>PAGDAYEG SA GINOO&amp;mdash;SA IYANG KATAHUM</category>
  <numbers><cebuano num="171"/><chinese num="141"/><english num="171"/><german num="171"/><korean num="141"/><portuguese num="86"/><russian num="35"/><spanish num="81"/><tagalog num="171"/></numbers>
  <creators>
	<author biodate="1905-1997" biolink="www.witnesslee.org">Translated from Witness Lee</author>
  </creators>
  <melody>| 0. 0 ._3/ | ._3 ._3/ ._1 ._3/ | ._2 ._1/ 6/( ._1/) 6/ | 5 3/ 6/( 5/) 3/ (break) | 2.( 2) 5/ | 5 5/ ._1 ._3/ | ._2 ._1/ 6/( ._1/) 6/ | 5 ._1/ ._3 ._2/ (break) | ._1.( ._1) (Chorus) ._2/ | ._2/ ._2/ ._2/ ._2/ ._3/ ._4/ | ._3. ._1 ._3/ | ._2/ ._2/ ._2/ ._2/ ._1/ 6/ (break) | 5.( 5) 5/ | 5 5/ ._1 ._3/ | ._2 ._1/ 6/( ._1/) 6/ | 5 ._1/ ._3 ._2/ | ._1.( ._1) 0/ |</melody>
  <notes>&amp;dagger; Usa ka tanom sa Daang Kalibutan nga mahal kaayo tungod sa humot nga dalag ug puting mga bulak niini. (A.S. 1:14, A.S.V.)</notes>
  <music>
	<midiref type="h" num="171"/>
  </music>
  <lyrics>
	<stanza type="verse" number="1">Ginoo's paghandom namo
Katam-is gibati;
Nangandoy sa hinanali
Nga malalin kami.</stanza>
	<stanza type="chorus" number="">Sama Ka sa bulak nga &amp;dagger;copher,
Namulak sa kaparrasan;
Katahum di ikatandi,
Gimahal, gidayeg!</stanza>
	<stanza type="verse" number="2">Way honing arang magdayeg's
Kahingpit's grasya Mo,
May tawo bang makapa'mulos
Sa gugma Mo's bug-os?</stanza>
	<stanza type="verse" number="3">Ang labing naglipay namo
Di gugma'g grasya Mo,
Kondi' Imong Kaugalingon
Nga nagtagbaw namo.</stanza>
	<stanza type="verse" number="4">Matahum pa sa matahum,
Tam-is pa sa tam-is;
Way lain's langit o yuta
Magtagbaw's tinguha.</stanza>
  </lyrics>
</hymn>
