<?xml version="1.0" encoding="utf-8"?>
<user xmlns="http://www.hymnal.net/user" version="1.0">
    <firstname>Lawrence S</firstname>
    <lastname>Manzer</lastname>
    <email>larrymanzer@sbcglobal.net</email>
    <password>payd9vyEOBisl9FMwpDAhA%3D%3D</password>
    <gender></gender>
    <country>United States</country>
    <ipaddress>99.16.84.47</ipaddress>
    <createdate>2013-09-11 09:25:32</createdate>
    <lastupdateddate>2013-09-11 09:25:32</lastupdateddate>
    <lastlogindate>2013-09-11 09:25:32</lastlogindate>
    <failedlogincount>0</failedlogincount>
    <favourites>
    </favourites>
</user>
