<?xml version="1.0" encoding="utf-8"?>
<!DOCTYPE html PUBLIC "-//W3C//DTD XHTML 1.0 Transitional//EN" "http://www.w3.org/TR/xhtml1/DTD/xhtml1-transitional.dtd">
<user>    <firstname>Odunayo</firstname>
    <lastname>Olowe</lastname>
    <email>ayoinspiration@hotmail.com</email>
    <password>%2FK%2FCvNptisS1ezePfv3pNA%3D%3D</password>
    <gender>M</gender>
    <country>ng</country>
    <ipaddress>41.222.70.17</ipaddress>
    <createdate>2010-04-28 02:36:13</createdate>
    <lastupdateddate>2010-04-28 02:36:15</lastupdateddate>
    <lastlogindate>2010-04-28 02:36:15</lastlogindate>
    <failedlogincount>0</failedlogincount>
    <favourites>
    </favourites>
</user>
