<?xml version="1.0" encoding="utf-8"?>
<user xmlns="http://www.hymnal.net/user" version="1.0">
    <firstname>Nicolette</firstname>
    <lastname>Allison</lastname>
    <email>nicky-b66@verizon.net</email>
    <password>nWNoryCRT6Be2OYJCKaXIA%3D%3D</password>
    <gender></gender>
    <country>United States</country>
    <ipaddress>74.101.17.38</ipaddress>
    <createdate>2013-01-26 17:55:44</createdate>
    <lastupdateddate>2013-01-26 17:55:44</lastupdateddate>
    <lastlogindate>2013-01-26 17:55:44</lastlogindate>
    <failedlogincount>0</failedlogincount>
    <favourites>
    </favourites>
</user>
