<?xml version="1.0" encoding="utf-8"?>
<hymn xmlns="http://www.hymnal.net/hymn">
  <title>Wat eerst winstgevend was, dat stelt nu niets meer voor</title>
  <index>true</index>
  <category>Ervaren van Christus&amp;mdash;als leven</category>
  <music>
  </music>
  <lyrics>
    <stanza type="verse" number="1">Wat eerst winstgevend was, dat stelt nu niets meer voor.
Jezus bevrijdde mij, van mijn persoon.
Alles wat ik hier had, maakt niet uit wat ’t was.
Dat is nu waardeloos, want ik win de Heer!</stanza>
    <stanza type="chorus" number="">Ik geef niet op!
Ik ren vooruit totdat mijn doel is bereikt.
Hij roept ons allen!
Ik ga nu door!
Ik win Hem meer en meer, want Hij is mijn keus.
Hij laat mij niet gaan!</stanza>
    <stanza type="verse" number="2">Laat alles achter je, strek je uit naar de Heer.
Twijfel niet aan je keus, dit is Zijn weg.
Groei in Hem elke dag, zo weet je wie Hij is.
Als je in Hem verblijft, wordt Hij steeds meer!</stanza>
  </lyrics>
</hymn>
