<?xml version="1.0" encoding="utf-8"?>
<user xmlns="http://www.hymnal.net/user" version="2.0">
  <roles>USER</roles>
  <firstname>Cindy</firstname>
  <lastname>Greenwood</lastname>
  <email>onewithhim@gmail.com</email>
  <password>$2y$10$Qn6JzM8LTJLxny0B.AZbt.inO1P8M50WXHY8g2WWiSA9hlojCO3mK</password>
  <gender/>
  <country>uk</country>
  <ipaddress>80.42.254.9</ipaddress>
  <createdate>2014-10-04 06:34:31</createdate>
  <lastupdateddate>2014-10-04 06:35:35</lastupdateddate>
  <lastlogindate>2014-10-04 06:35:35</lastlogindate>
  <failedlogincount>0</failedlogincount>
  <favourites>
  </favourites>
</user>
