<?xml version="1.0" encoding="utf-8"?>
<hymn xmlns="http://www.hymnal.net/hymn">
  <title>Sim, do céu virá o Senhor e a trombeta soará</title>
  <index>true</index>
  <category>Esperar E Vigiar</category>
  <numbers><chinese num="754"/><english num="1354"/><french num="182"/><portuguese num="482"/><russian num="339"/><spanish num="437"/><tagalog num="1354"/></numbers>
  <music>
    <midiref type="h" num="1226"/>
  </music>
  <lyrics>
    <stanza type="verse" number="1">Sim, do céu virá o Senhor e a trombeta soará;
Não mais morte, os que dormem viverão.
Sim, do céu virá o Senhor, os vivos arrebatará;
Nossos corpos, pois, transfigurar-se-ão.</stanza>
    <stanza type="chorus" number="">Ao voltar Jesus em glória,
Majestoso, em vitória,
Vamos contemplar-Lhe a glória,
Nós, Seus santos, vamos transformados ser.</stanza>
    <stanza type="verse" number="2">Sim, do céu virá o Senhor, manhã brilhante nascerá;
Noite escura, dor e pranto findarão.
Sim, do céu virá o Senhor, gloriosos dias vão chegar;
Nunca mais murmúrios, trevas, corrupção.</stanza>
    <stanza type="verse" number="3">Sim, do céu virá o Senhor, brilhante Estrela da Manhã;
Quem vigia vai ganhar seu galardão.
Sol nascente da justiça, o Senhor irá reinar;
Restaurada a terra e toda a criação.</stanza>
    <stanza type="verse" number="4">Sim, do céu virá o Senhor, mui vigilantes vamos ser;
Vamos nos cingir e óleo armazenar.
Como servos bons, fiéis, Seu ministério aqui cumprir;
Nossos dons jamais devemos enterrar.</stanza>
  </lyrics>
</hymn>
