<?xml version="1.0" encoding="utf-8"?>
<hymn xmlns="http://www.hymnal.net/hymn">
  <title>Herr, Du bist mein Leben</title>
  <index>true</index>
  <category>DIE GEMEINDE&amp;mdash;Ihr Aufbau</category>
  <numbers><cebuano num="841"/><chinese num="381"/><dutch num="3"/><english num="841"/><french num="149"/><german num="841"/><korean num="381"/><portuguese num="236"/><russian num="133"/><spanish num="359"/><tagalog num="841"/></numbers>
  <creators>
	<author biodate="1905-1997" biolink="www.witnesslee.org">Translated from Witness Lee</author>
  </creators>
  <melody>| 3. 3/ 3 2 | 1 - 6_. - | 4. 3/ 2 1 | 7_. - - - (break) | 5 2 3 4 | 3 - 1 - | 2. 1/ 7_. 6_. | 5_. - - - (break) | 5_. 5_. 6_. 7_. | 2 - 1 - | 1 1 4 4 | 3 - - - (break) | 1 2 3 4 | 5 - 5_. - | 6_. 4 3 2 | 1 - - - |</melody>
  <layout>
	<singingstanza>Herr, Du bist mein Le -- ben, Lebst und wohnst in mir; Und die Fül -- le Got -- tes  Schenkst Du mir mit Dir. Durch Dein rei -- nes We -- sen Bin ge -- hei -- ligt ich, Dei -- ne Auf -- er -- ste -- hung Bringt den Sieg in mich.</singingstanza>
	<columns>2</columns>
  </layout>
  <music>
	<midiref type="h" num="841"/>
  </music>
  <lyrics>
	<stanza type="verse" number="1">Herr, Du bist mein Leben,
    Lebst und wohnst in mir;
Und die Fülle Gottes 
    Schenkst Du mir mit Dir.
Durch Dein reines Wesen
    Bin geheiligt ich,
Deine Auferstehung
    Bringt den Sieg in mich.</stanza>
	<stanza type="verse" number="2">Herr, Dein reines Leben,
    Hell erleuchtet mich,
Und es bringt Gemeinschaft 
    Stets im Geist mit sich;
Was Du forderst, stillt es,
    Und was mangelt mir,
Reinigt mich vollkommen,
    Lässt mich stehn in Dir.</stanza>
	<stanza type="verse" number="3">Deine Salbung dringe
    Tief in mich hinein.
Geist und Seele sollen
    Ganz durchsättigt sein;
Wandle jeden Teil um
    Bis ich Dir gleich bin;
Bis ich durch Dein Leben
    Reif bin und Dir dien.</stanza>
	<stanza type="verse" number="4">Herr, Dein reiches Leben
    Ständig fließt so treu,
Wunderbar erfrischts mich,
    Kräftigt mich stets neu.
Tod ist ganz verschlungen,
    Schwaches Kraft anzieht,
Ketten sind zerbrochen,
    Schwermut wird zum Lied.</stanza>
	<stanza type="verse" number="5">Herr, ich will mich geben
    Völlig und ganz Dir,
Dass Dein Herzenssehnen
    Wird erfüllt in mir.
Möcht nicht mehr versuchen
    Zu verbessern mich,
Herr, in mir nun wirke,
    Möcht nicht hindern Dich.</stanza>
	<stanza type="verse" number="6">Möchte ganz aufhören,
    Mich umsonst zu mühn,
Leben soll mich ändern,
    Nun für Dich möcht glühn;
Bau mich auf mit andern,
    Bis in uns Du siehst,
Deinen vollen Ausdruck,
    Du verherrlicht bist.</stanza>
  </lyrics>
</hymn>
