<?xml version="1.0" encoding="utf-8"?>
<hymn xmlns="http://www.hymnal.net/hymn">
  <title>為這筵席我獻感謝</title>
  <index>true</index>
  <category>讚美主－對祂的記念</category>
  <numbers><cebuano num="221"/><chinese num="178"/><dutch num="56"/><english num="221"/><french num="36"/><german num="221"/><korean num="178"/><portuguese num="115"/><russian num="42"/><spanish num="97"/><tagalog num="221"/></numbers>
  <creators>
	<author biodate="1905-1997" biolink="www.witnesslee.org">Translated from Witness Lee</author>
  </creators>
  <melody>| 5. 4#/ 6 5 | 5. 3/ 5 4 | 3. 2/ 4. 3/ | 3. 2/ 1 - (break) |  5. 4#/ 6 5 | 5. 3/ 5 4 | 3. 2/ 4/ 2/ 6_./ 7_./ | 1 - - - (break) | 2. 3/ 4/( 3/) 2 | 3. 6/ 5 3 | 2. 3/ 4/( 3/) 2 | 3. 6/ 5 - (break) | 5. 3/ ._1. 7/ | 6/( 7) 6/ 5 3 | 1. 2/ 3/( 5) 4/ | 3. 2/ 1 - (break) | (Chorus) 5. 4#/ 6 5 | 3 - 2 - | 4. 3/ 4 6 | 5 - 3 - (break) | 5. 4#/ 5 ._1 | 7 6 5 4 | 3. 5/ 4 2 | 1 - - 0 |</melody>
  <layout>
	<singingstanza>為 這 筵 席 我 獻 感 謝， 餅、 杯 在 此 同 陳 列； 藉 此 享 受 你 的 自 己， 神 聖 愛 筵 何 超 絕。 這 餅 是 你 所 捨 身 體， 我 們 在 此 同 分 享； 這 杯 是 你 所 流 寶 血， 我 們 在 此 同 飲 嘗。 看， 這 神 聖 筵 席！ 其 上 何 等 表 記！ 意 義 深 厚， 永 垂 不 朽， 人 知 何 能 及！</singingstanza>
  </layout>
  <music>
	<midiref type="h" num="62"/>
  </music>
  <lyrics>
	<stanza type="verse" number="1">為這筵席我獻感謝，
餅、杯在此同陳列；
藉此享受你的自己，
神聖愛筵何超絕。
這餅是你所捨身體，
我們在此同分享；
這杯是你所流寶血，
我們在此同飲嘗。</stanza>
	<stanza type="chorus" number="">看，這神聖筵席！
其上何等表記！
意義深厚，永垂不朽，
人知何能及！</stanza>
	<stanza type="verse" number="2">藉著你的救贖之死，
你將生命來分賜；
你將自己給了我們，
要我有分你所是。
藉著分享這餅、這杯，
我們陳列你的死；
在此喫喝你的自己，
如此記念到永世。</stanza>
	<stanza type="verse" number="3">這餅在此也是指明
你那奧祕的身體；
藉此與眾肢體交通，
見證身體的合一。
這杯也是神聖福杯，
我們現在所祝福；
藉著你血我們交通，
與你所有的聖徒。</stanza>
	<stanza type="verse" number="4">你是我們永遠的分，
在此豫嘗何有福；
我們等候你的國度，
你的顯現我催促。
當你顯現在你國度，
同著得勝的聖徒，
重新享受你的自己，
作你心愛的新婦。</stanza>
  </lyrics>
</hymn>
