<?xml version="1.0" encoding="utf-8"?>
<hymn xmlns="http://www.hymnal.net/hymn">
  <title>如果爭戰兇猛</title>
  <index>true</index>
  <category>屬靈的爭戰－讚美</category>
  <numbers><cebuano num="876"/><chinese num="639"/><english num="876"/><korean num="639"/><tagalog num="876"/></numbers>
  <creators>
	<author biodate="1903-1972" biolink="www.watchmannee.org">Translated from Watchman Nee</author>
  </creators>
  <melody>| 0 - 5 - | 5 3 3 1 | 2 - - - | 5 - 6 4# | 5 - 5 - (break) | 5 3 4 5 | 6 - - - | 2 - 3 2 | 1 - 0 - |</melody>
  <layout>
	<singingstanza>如 果 爭 戰 兇 猛， 仇 敵 強 盛， 你 當 堅 信 主 話， 並 發 歌 聲。</singingstanza>
  </layout>
  <music>
	<midiref type="h" num="876"/>
  </music>
  <lyrics>
	<stanza type="verse" number="1">如果爭戰兇猛，
仇敵強盛，
你當堅信主話，
並發歌聲。</stanza>
	<stanza type="verse" number="2">只要呼喊一聲，
就要得勝，
不要啞口不作
反抗見證。</stanza>
	<stanza type="verse" number="3">你靈現在鬱悶，
好像無能，
你若藉血禱告，
就要高升。</stanza>
	<stanza type="verse" number="4">仇敵雖然蠻橫，
你可與爭，
如果堅守地位，
不久就勝。</stanza>
	<stanza type="verse" number="5">所以應當發聲，
證明主勝，
光景雖然黑暗，
但必變更。</stanza>
  </lyrics>
</hymn>
