<?xml version="1.0" encoding="utf-8"?>
<user xmlns="http://www.hymnal.net/user" version="1.0">    <firstname>Almer</firstname>
    <lastname>Natividad</lastname>
    <email>almer_daxenreplica@yahoo.com</email>
    <password>lau4kFVQzR6GA9SZw9fpug%3D%3D</password>
    <gender>M</gender>
    <country>ph</country>
    <ipaddress>121.97.192.55</ipaddress>
    <createdate>2012-08-18 02:19:47</createdate>
    <lastupdateddate>2012-08-18 11:14:42</lastupdateddate>
    <lastlogindate>2012-08-18 11:13:23</lastlogindate>
    <failedlogincount>0</failedlogincount>
    <favourites>
        <fav category="default" type="cb" num="1170">Ginoo akong Magbalantay</fav>
        <fav category="default" type="cb" num="1237">Mahimayaong iglesia! Gidala ta daygon S'ya</fav>
        <fav category="default" type="cb" num="396">Nagpadayon sa pagtungas</fav>
        <fav category="default" type="h" num="1226">Oh, the church of Christ is glorious</fav>
    </favourites>
</user>
